odoo/addons/project_forecast_line/README.rst
odoo/addons/project_forecast_line/__init__.py
odoo/addons/project_forecast_line/__manifest__.py
odoo/addons/project_forecast_line/data/ir_cron.xml
odoo/addons/project_forecast_line/data/project_data.xml
odoo/addons/project_forecast_line/demo/forecast_role.xml
odoo/addons/project_forecast_line/demo/hr_employee.xml
odoo/addons/project_forecast_line/demo/hr_job.xml
odoo/addons/project_forecast_line/demo/product.xml
odoo/addons/project_forecast_line/demo/project.xml
odoo/addons/project_forecast_line/demo/res_users.xml
odoo/addons/project_forecast_line/demo/sale.xml
odoo/addons/project_forecast_line/i18n/es.po
odoo/addons/project_forecast_line/i18n/fr.po
odoo/addons/project_forecast_line/i18n/it.po
odoo/addons/project_forecast_line/i18n/project_forecast_line.pot
odoo/addons/project_forecast_line/models/__init__.py
odoo/addons/project_forecast_line/models/forecast_line.py
odoo/addons/project_forecast_line/models/forecast_line_mixin.py
odoo/addons/project_forecast_line/models/forecast_role.py
odoo/addons/project_forecast_line/models/hr_employee.py
odoo/addons/project_forecast_line/models/hr_leave.py
odoo/addons/project_forecast_line/models/product_template.py
odoo/addons/project_forecast_line/models/project_project_stage.py
odoo/addons/project_forecast_line/models/project_task.py
odoo/addons/project_forecast_line/models/res_company.py
odoo/addons/project_forecast_line/models/res_config_settings.py
odoo/addons/project_forecast_line/models/resource_calendar_leaves.py
odoo/addons/project_forecast_line/models/sale_order.py
odoo/addons/project_forecast_line/models/sale_order_line.py
odoo/addons/project_forecast_line/readme/CONFIGURATION.rst
odoo/addons/project_forecast_line/readme/CONTRIBUTORS.rst
odoo/addons/project_forecast_line/readme/DESCRIPTION.rst
odoo/addons/project_forecast_line/readme/USAGE.rst
odoo/addons/project_forecast_line/security/forecast_line_security.xml
odoo_addon_project_forecast_line-15.0.1.3.4.1.dist-info/METADATA
odoo_addon_project_forecast_line-15.0.1.3.4.1.dist-info/WHEEL
odoo_addon_project_forecast_line-15.0.1.3.4.1.dist-info/top_level.txt
odoo_addon_project_forecast_line-15.0.1.3.4.1.dist-info/RECORD
